doctr/__init__.py
doctr/__main__.py
doctr/_version.py
doctr/common.py
doctr/gitlab.py
doctr/local.py
doctr/travis.py
doctr/tests/__init__.py
doctr/tests/test_local.py
doctr/tests/test_travis.py
doctr-1.9.0.dist-info/LICENSE
doctr-1.9.0.dist-info/METADATA
doctr-1.9.0.dist-info/WHEEL
doctr-1.9.0.dist-info/entry_points.txt
doctr-1.9.0.dist-info/top_level.txt
doctr-1.9.0.dist-info/RECORD
